[{
    "name":"מסיבת סיום מיטב",
    "location":"משפחת סילברמן",
    "address":"החיטה 33",
    "city":"ינוב",
    "fromDate":"2017-07-13",
    "toDate":"2017-07-13",
    "day":"ה",
    "type":"מיטב",
    "status":"לא פעיל"
},
{
    "name":"אירוע פתיחת עונה אתנה",
    "location":"אולם הישגי",
    "address":"מכון ווינגיט",
    "city":"מכון ווינגיט",
    "fromDate":"2017-10-18",
    "toDate":"2017-10-18",
    "day":"ד",
    "type":"אתנה",
    "status":"לא פעיל"
},
{
    "name":"אליפות מיטב",
    "location":"היכל הספורט מטרו-ווסט",
    "address":"הפלמח 4",
    "city":"רעננה",
    "fromDate":"2017-10-21",
    "toDate":"2017-10-21",
    "day":"ש",
    "type":"מיטב",
    "status":"לא פעיל"
},
{
    "name":"גביע האיגוד - מס' 2",
    "location":"היכל הספורט מטרו-ווסט",
    "address":"הפלמח 4",
    "city":"רעננה",
    "fromDate":"2017-11-24",
    "toDate":"2017-11-24",
    "day":"ש",
    "type":"איגוד",
    "status":"לא פעיל"
},
{
    "name":"טורניר החורף בג'ודו",
    "location":"אולם ספורט",
    "address":"רמבם 35",
    "city":"פרדסיה",
    "fromDate":"2017-12-15",
    "toDate":"2017-12-15",
    "day":"ו",
    "type":"מיטב",
    "status":"פעיל"
},
{
    "name":"מחנה אימונים בינלאומי",
    "location":"",
    "address":"מלון",
    "city":"בארדנוצ'יה, איטליה",
    "fromDate":"2017-12-25",
    "toDate":"2017-12-31",
    "day":"א-ש",
    "type":"איגוד",
    "status":"פעיל"
},
{
    "name":"פסטיבל הג'ודו",
    "location":"קניון אייס מול",
    "address":"רמבם 35",
    "city":"אילת",
    "fromDate":"2018-01-17",
    "toDate":"2018-01-20",
    "day":"ד-ש",
    "type":"איגוד",
    "status":"פעיל"
}]